{
  "sinif": "9",
  "ders": "İşletmelerde Mesleki Eğitim (Ortak)-9",
  "plan": [
    {
      "ÜNİTE": "1.  İŞ SAĞLIĞI VE GÜVENLİĞİ",
      "AY": "EYLÜL",
      "HAFTA": "1. Hafta:\n08-12 Eylül",
      "SAAT": "32",
      "KONU": "İş sağlığı ve güvenliği çalışanların yasal hak ve sorumlulukları",
      "BELİRLİ GÜN VE HAFTALAR": "Uluslararası Temiz Hava Günü",
      "KAZANIM": "1. İş sağlığı ve güvenliği çalışanların yasal hak ve sorumlulukları ile iş kazalarından doğabilecek hukuki sonuçları açıklar."
    },
    {
      "ÜNİTE": "1.  İŞ SAĞLIĞI VE GÜVENLİĞİ",
      "AY": "EYLÜL",
      "HAFTA": "2. Hafta:\n15-19 Eylül",
      "SAAT": "32",
      "KONU": "MESLEKİ hastalıkları ve korunma yöntemleri",
      "BELİRLİ GÜN VE HAFTALAR": "İlköğretim Haftası Mevlid-i Nebî Haftası Öğrenciler Günü Gaziler Günü",
      "KAZANIM": "2. MESLEKİ hastalıkları ve bu hastalıklardan korunma yöntemlerini açıklar."
    },
    {
      "ÜNİTE": "1.  İŞ SAĞLIĞI VE GÜVENLİĞİ",
      "AY": "EYLÜL",
      "HAFTA": "3. Hafta:\n22-26 Eylül",
      "SAAT": "32",
      "KONU": "İş kazaları ve korunma yöntemleri",
      "KAZANIM": "3. İş yerinde oluşabilecek iş kazalarına karşı gerekli tedbirleri alır."
    },
    {
      "ÜNİTE": "1.  İŞ SAĞLIĞI VE GÜVENLİĞİ",
      "AY": "EYLÜL",
      "HAFTA": "4. Hafta:\n29 Eylül-03 Ekim",
      "SAAT": "32",
      "KONU": "İş kazaları ve korunma yöntemleri",
      "BELİRLİ GÜN VE HAFTALAR": "Disleksi Haftası Dünya Disleksi Günü",
      "KAZANIM": "3. İş yerinde oluşabilecek iş kazalarına karşı gerekli tedbirleri alır."
    },
    {
      "ÜNİTE": "2. MOTORLU ARAÇLAR TEKNOLOJİSİ ALANINDA İŞ SAĞLIĞI VE GÜVENLİĞİ",
      "AY": "EKIM",
      "HAFTA": "5. Hafta:\n06-10 Ekim",
      "SAAT": "32",
      "KONU": "Motorculukta kullanılan el aletlerinde güvenlik",
      "BELİRLİ GÜN VE HAFTALAR": "Ahilik Kültürü Haftası",
      "KAZANIM": "1. El aletlerini iş sağlığı ve güvenliği tedbirlerini alarak güvenli kullanır."
    },
    {
      "ÜNİTE": "2. MOTORLU ARAÇLAR TEKNOLOJİSİ ALANINDA İŞ SAĞLIĞI VE GÜVENLİĞİ",
      "AY": "EKIM",
      "HAFTA": "6. Hafta:\n13-17 Ekim",
      "SAAT": "32",
      "KONU": "Motorculukta kullanılan el aletlerinde güvenlik",
      "KAZANIM": "1. El aletlerini iş sağlığı ve güvenliği tedbirlerini alarak güvenli kullanır."
    },
    {
      "ÜNİTE": "2. MOTORLU ARAÇLAR TEKNOLOJİSİ ALANINDA İŞ SAĞLIĞI VE GÜVENLİĞİ",
      "AY": "EKIM",
      "HAFTA": "7. Hafta:\n20-24 Ekim",
      "SAAT": "32",
      "KONU": "Motor atölyelerinde kullanılan tezgahlarda güvenli çalışma",
      "KAZANIM": "2. Motor atölyesindeki çalışma ortamını hazırlar."
    },
    {
      "ÜNİTE": "2. MOTORLU ARAÇLAR TEKNOLOJİSİ ALANINDA İŞ SAĞLIĞI VE GÜVENLİĞİ",
      "AY": "EKIM",
      "HAFTA": "8. Hafta:\n27-31 Ekim",
      "SAAT": "32",
      "KONU": "Motor atölyelerinde güvenli lift kriko kullanımı",
      "BELİRLİ GÜN VE HAFTALAR": "Cumhuriyet Bayramı",
      "KAZANIM": "3. Aracı lift veveya kriko ile güvenli bir şekilde kaldırır."
    },
    {
      "ÜNİTE": "2. MOTORLU ARAÇLAR TEKNOLOJİSİ ALANINDA İŞ SAĞLIĞI VE GÜVENLİĞİ",
      "AY": "KASIM",
      "HAFTA": "9. Hafta:\n03-07 Kasım",
      "SAAT": "32",
      "KONU": "Motor atölyelerinde yanıcı patlayıcı parlayıcı maddeler ile güvenli çalışma",
      "BELİRLİ GÜN VE HAFTALAR": "Kızılay Haftası Organ Bağışı ve Nakli Haftası Lösemili Çocuklar Haftası",
      "KAZANIM": "1. Dönem 1. Sınav 4. Yanıcı parlayıcı ve patlayıcı maddeler ile ilgili güvenlik tedbirlerini alır."
    },
    {
      "ÜNİTE": "1. Dönem Ara Tatili",
      "AY": "KASIM",
      "HAFTA": "10. Hafta:\n10-14 Kasım",
      "SAAT": "32",
      "KONU": "1. Dönem Ara Tatili",
      "BELİRLİ GÜN VE HAFTALAR": "Atatürk Haftası Afet Eğitimi Hazırlık Günü Dünya Diyabet Günü",
      "KAZANIM": "1. Dönem Ara Tatili"
    },
    {
      "ÜNİTE": "3. TEMEL SERVİS EKİPMANLARI",
      "AY": "KASIM",
      "HAFTA": "11. Hafta:\n17-21 Kasım",
      "SAAT": "32",
      "KONU": "El aletleri",
      "BELİRLİ GÜN VE HAFTALAR": "Dünya FELSEFE Günü Dünya Çocuk Hakları Günü",
      "KAZANIM": "1. Motorculuk el aletlerini amacına ve yerine uygun şekilde kullanır."
    },
    {
      "ÜNİTE": "3. TEMEL SERVİS EKİPMANLARI",
      "AY": "KASIM",
      "HAFTA": "12. Hafta:\n24-28 Kasım",
      "SAAT": "32",
      "KONU": "El aletleri",
      "BELİRLİ GÜN VE HAFTALAR": "Ağız ve Diş Sağlığı Haftası Öğretmenler Günü",
      "KAZANIM": "1. Motorculuk el aletlerini amacına ve yerine uygun şekilde kullanır."
    },
    {
      "ÜNİTE": "3. TEMEL SERVİS EKİPMANLARI",
      "AY": "ARALIK",
      "HAFTA": "13. Hafta:\n01-05 Aralık",
      "SAAT": "32",
      "KONU": "El aletleri",
      "BELİRLİ GÜN VE HAFTALAR": "Dünya Engelliler Günü Dünya Madenciler Günü Türk Kadınına Seçme ve Seçilme Hakkının Verilişi",
      "KAZANIM": "1. Motorculuk el aletlerini amacına ve yerine uygun şekilde kullanır."
    },
    {
      "ÜNİTE": "3. TEMEL SERVİS EKİPMANLARI",
      "AY": "ARALIK",
      "HAFTA": "14. Hafta:\n08-12 Aralık",
      "SAAT": "32",
      "KONU": "Mesleğe özel el takımları",
      "BELİRLİ GÜN VE HAFTALAR": "Mevlana Haftası İnsan Hakları ve Demokrasi Haftası",
      "KAZANIM": "2. Motorculuk özel el takımlarını amacına ve yerine uygun şekilde kullanır."
    },
    {
      "ÜNİTE": "3. TEMEL SERVİS EKİPMANLARI",
      "AY": "ARALIK",
      "HAFTA": "15. Hafta:\n15-19 Aralık",
      "SAAT": "32",
      "KONU": "Mesleğe özel el takımları",
      "BELİRLİ GÜN VE HAFTALAR": "Tutum Yatırım ve Türk Malları Haftası",
      "KAZANIM": "2. Motorculuk özel el takımlarını amacına ve yerine uygun şekilde kullanır."
    },
    {
      "ÜNİTE": "3. TEMEL SERVİS EKİPMANLARI",
      "AY": "ARALIK",
      "HAFTA": "16. Hafta:\n22-26 Aralık",
      "SAAT": "32",
      "KONU": "Mesleğe özel el takımları",
      "BELİRLİ GÜN VE HAFTALAR": "Mehmet Akif Ersoyu Anma Haftası",
      "KAZANIM": "2. Motorculuk özel el takımlarını amacına ve yerine uygun şekilde kullanır."
    },
    {
      "ÜNİTE": "3. TEMEL SERVİS EKİPMANLARI",
      "AY": "ARALIK",
      "HAFTA": "17. Hafta:\n29 Aralık-02 Ocak",
      "SAAT": "32",
      "KONU": "Motorlu Araç kaldırma",
      "KAZANIM": "3. Motorlu araçları güvenlik kurallarına uygun olarak kaldırma ve sehpalama yapar."
    },
    {
      "ÜNİTE": "3. TEMEL SERVİS EKİPMANLARI",
      "AY": "OCAK",
      "HAFTA": "18. Hafta:\n05-09 Ocak",
      "SAAT": "32",
      "KONU": "Motorlu Araç kaldırma",
      "BELİRLİ GÜN VE HAFTALAR": "Enerji Tasarrufu Haftası",
      "KAZANIM": "1. Dönem 2. Sınav 3. Motorlu araçları güvenlik kurallarına uygun olarak kaldırma ve sehpalama yapar."
    },
    {
      "ÜNİTE": "Etkinlik Haftası",
      "AY": "OCAK",
      "HAFTA": "19. Hafta:\n12-16 Ocak",
      "SAAT": "32",
      "KONU": "Etkinlik Haftası",
      "KAZANIM": "Etkinlik Haftası"
    },
    {
      "ÜNİTE": "Yarıyıl Tatili",
      "AY": "OCAK",
      "HAFTA": "20. Hafta:\n19-23 Ocak",
      "SAAT": "32",
      "KONU": "Yarıyıl Tatili",
      "KAZANIM": "Yarıyıl Tatili"
    },
    {
      "ÜNİTE": "Yarıyıl Tatili",
      "AY": "OCAK",
      "HAFTA": "21. Hafta:\n26-30 Ocak",
      "SAAT": "32",
      "KONU": "Yarıyıl Tatili",
      "KAZANIM": "Yarıyıl Tatili"
    },
    {
      "ÜNİTE": "3. TEMEL SERVİS EKİPMANLARI",
      "AY": "ŞUBAT",
      "HAFTA": "22. Hafta:\n02-06 ubat",
      "SAAT": "32",
      "KONU": "Motorlu Araç kaldırma",
      "KAZANIM": "3. Motorlu araçları güvenlik kurallarına uygun olarak kaldırma ve sehpalama yapar."
    },
    {
      "ÜNİTE": "3. TEMEL SERVİS EKİPMANLARI",
      "AY": "ŞUBAT",
      "HAFTA": "23. Hafta:\n09-13 ubat",
      "SAAT": "32",
      "KONU": "Ölçü aletleri",
      "KAZANIM": "4. Ölçü aletleri ile ölçme ve kontrol işlemlerini yapar."
    },
    {
      "ÜNİTE": "3. TEMEL SERVİS EKİPMANLARI",
      "AY": "ŞUBAT",
      "HAFTA": "24. Hafta:\n16-20 ubat",
      "SAAT": "32",
      "KONU": "Ölçü aletleri",
      "KAZANIM": "4. Ölçü aletleri ile ölçme ve kontrol işlemlerini yapar."
    },
    {
      "ÜNİTE": "3. TEMEL SERVİS EKİPMANLARI",
      "AY": "ŞUBAT",
      "HAFTA": "25. Hafta:\n23-27 ubat",
      "SAAT": "32",
      "KONU": "Ölçü aletleri",
      "BELİRLİ GÜN VE HAFTALAR": "Vergi Haftası Yeşilay Haftası",
      "KAZANIM": "4. Ölçü aletleri ile ölçme ve kontrol işlemlerini yapar."
    },
    {
      "ÜNİTE": "4. TEMEL MEKANİK İŞLEMLER",
      "AY": "MART",
      "HAFTA": "26. Hafta:\n02-06 Mart",
      "SAAT": "32",
      "KONU": "Çalışma alanını düzenleme",
      "BELİRLİ GÜN VE HAFTALAR": "Girişimcilik Haftası",
      "KAZANIM": "1. Çalışma alanını düzenler."
    },
    {
      "ÜNİTE": "4. TEMEL MEKANİK İŞLEMLER",
      "AY": "MART",
      "HAFTA": "27. Hafta:\n09-13 Mart",
      "SAAT": "32",
      "KONU": "Çalışma alanını düzenleme",
      "BELİRLİ GÜN VE HAFTALAR": "Bilim ve Teknoloji Haftası İstiklâl Marşının Kabulü ve Mehmet Akif Ersoyu Anma Günü",
      "KAZANIM": "1. Çalışma alanını düzenler."
    },
    {
      "ÜNİTE": "2. Dönem Ara Tatili",
      "AY": "MART",
      "HAFTA": "28. Hafta:\n16-20 Mart",
      "SAAT": "32",
      "KONU": "2. Dönem Ara Tatili",
      "BELİRLİ GÜN VE HAFTALAR": "Tüketiciyi Koruma Haftası Türk Dünyası ve Toplulukları Haftası",
      "KAZANIM": "2. Dönem Ara Tatili"
    },
    {
      "ÜNİTE": "4. TEMEL MEKANİK İŞLEMLER",
      "AY": "MART",
      "HAFTA": "29. Hafta:\n23-27 Mart",
      "SAAT": "32",
      "KONU": "Kesme ve eğeleme",
      "BELİRLİ GÜN VE HAFTALAR": "Orman Haftası Dünya Tiyatrolar Günü",
      "KAZANIM": "2. İş parçasına teknik kurallara uygun şekilde kesme ve eğeleme yapar."
    },
    {
      "ÜNİTE": "4. TEMEL MEKANİK İŞLEMLER",
      "AY": "MART",
      "HAFTA": "30. Hafta:\n30 Mart-03 Nisan",
      "SAAT": "32",
      "KONU": "Kesme ve eğeleme",
      "BELİRLİ GÜN VE HAFTALAR": "Kütüphaneler Haftası Kanser Haftası Dünya Otizm Farkındalık Günü",
      "KAZANIM": "2. İş parçasına teknik kurallara uygun şekilde kesme ve eğeleme yapar."
    },
    {
      "ÜNİTE": "4. TEMEL MEKANİK İŞLEMLER",
      "AY": "NISAN",
      "HAFTA": "31. Hafta:\n06-10 Nisan",
      "SAAT": "32",
      "KONU": "Kesme ve eğeleme",
      "BELİRLİ GÜN VE HAFTALAR": "Kanser Haftası Dünya Sağlık GününDünya Sağlık Haftası Kişisel Verileri Koruma Günü",
      "KAZANIM": "2. Dönem 1. Sınav 2. İş parçasına teknik kurallara uygun şekilde kesme ve eğeleme yapar."
    },
    {
      "ÜNİTE": "4. TEMEL MEKANİK İŞLEMLER",
      "AY": "NISAN",
      "HAFTA": "32. Hafta:\n13-17 Nisan",
      "SAAT": "32",
      "KONU": "Markalama işlemi",
      "BELİRLİ GÜN VE HAFTALAR": "Turizm Haftası",
      "KAZANIM": "3. İş parçası üzerine teknik kurallara uygun şekilde markalama yapar."
    },
    {
      "ÜNİTE": "4. TEMEL MEKANİK İŞLEMLER",
      "AY": "NISAN",
      "HAFTA": "33. Hafta:\n20-24 Nisan",
      "SAAT": "32",
      "KONU": "Markalama işlemi",
      "BELİRLİ GÜN VE HAFTALAR": "Ulusal Egemenlik ve Çocuk Bayramı",
      "KAZANIM": "3. İş parçası üzerine teknik kurallara uygun şekilde markalama yapar.                                                                                                                                                            ATATÜRK ün çocuklara verdiği önemi bilir."
    },
    {
      "ÜNİTE": "4. TEMEL MEKANİK İŞLEMLER",
      "AY": "NISAN",
      "HAFTA": "34. Hafta:\n27 Nisan-01 Mayıs",
      "SAAT": "32",
      "KONU": "Temel taşlama işlemleri",
      "BELİRLİ GÜN VE HAFTALAR": "Kûtül Amâre Zaferi",
      "KAZANIM": "4. İş parçasının teknik kurallara uygun şekilde temel taşlama işlemlerini yapar."
    },
    {
      "ÜNİTE": "4. TEMEL MEKANİK İŞLEMLER",
      "AY": "MAYIS",
      "HAFTA": "35. Hafta:\n04-08 Mayıs",
      "SAAT": "32",
      "KONU": "Temel taşlama işlemleri",
      "BELİRLİ GÜN VE HAFTALAR": "Bilişim Haftası Trafik ve İlkyardım Haftası İş Sağlığı ve Güvenliği Haftası",
      "KAZANIM": "4. İş parçasının teknik kurallara uygun şekilde temel taşlama işlemlerini yapar."
    },
    {
      "ÜNİTE": "4. TEMEL MEKANİK İŞLEMLER",
      "AY": "MAYIS",
      "HAFTA": "36. Hafta:\n11-15 Mayıs",
      "SAAT": "32",
      "KONU": "Metallerin delinmesi",
      "BELİRLİ GÜN VE HAFTALAR": "Engelliler Haftası Vakıflar Haftası",
      "KAZANIM": "5. İş parçası üzerine kurallara uygun şekilde delik açar."
    },
    {
      "ÜNİTE": "4. TEMEL MEKANİK İŞLEMLER",
      "AY": "MAYIS",
      "HAFTA": "37. Hafta:\n18-22 Mayıs",
      "SAAT": "32",
      "KONU": "Metallerin delinmesi",
      "BELİRLİ GÜN VE HAFTALAR": "Müzeler Haftası Atatürkü Anma ve Gençlik ve Spor Bayramı",
      "KAZANIM": "5. İş parçası üzerine kurallara uygun şekilde delik açar.                                                                                                                                                                                         ATATÜRKün Türk Gençliğine verdiği önemi bilir"
    },
    {
      "ÜNİTE": "4. TEMEL MEKANİK İŞLEMLER",
      "AY": "MAYIS",
      "HAFTA": "38. Hafta:\n25-29 Mayıs",
      "SAAT": "32",
      "KONU": "Diş açma",
      "BELİRLİ GÜN VE HAFTALAR": "Etik Günü İstanbulun Fethi",
      "KAZANIM": "6. İş parçası üzerine kurallara uygun şekilde diş açar."
    },
    {
      "ÜNİTE": "4. TEMEL MEKANİK İŞLEMLER",
      "AY": "HAZIRAN",
      "HAFTA": "39. Hafta:\n01-05 Haziran",
      "SAAT": "32",
      "KONU": "Diş açma",
      "BELİRLİ GÜN VE HAFTALAR": "Etik Günü Hayat Boyu Öğrenme Haftası",
      "KAZANIM": "2. Dönem 2. Sınav 6. İş parçası üzerine kurallara uygun şekilde diş açar."
    },
    {
      "ÜNİTE": "4. TEMEL MEKANİK İŞLEMLER",
      "AY": "HAZIRAN",
      "HAFTA": "40. Hafta:\n08-12 Haziran",
      "SAAT": "2",
      "KONU": "Perçinleme",
      "BELİRLİ GÜN VE HAFTALAR": "Etik Günü Çevre ve İklim Değişikliği Haftası",
      "KAZANIM": "7. İş parçasına teknik kurallara uygun şekilde perçinleme yapar."
    },
    {
      "ÜNİTE": "4. TEMEL MEKANİK İŞLEMLER",
      "AY": "HAZIRAN",
      "HAFTA": "41. Hafta:\n15-19 Haziran",
      "SAAT": "32",
      "KONU": "Perçinleme",
      "BELİRLİ GÜN VE HAFTALAR": "Etik Günü",
      "KAZANIM": "7. İş parçasına teknik kurallara uygun şekilde perçinleme yapar."
    },
    {
      "ÜNİTE": "Etkinlik Haftası",
      "AY": "HAZIRAN",
      "HAFTA": "42. Hafta:\n22-26 Haziran",
      "SAAT": "32",
      "KONU": "Etkinlik Haftası",
      "BELİRLİ GÜN VE HAFTALAR": "Etik Günü",
      "KAZANIM": "Etkinlik Haftası"
    }
  ]
}
