{
  "sinif": "11",
  "ders": "ÇALGI TOPLULUKLARI (BATI MZĞ)(YEN*)",
  "plan": [
    {
      "AY": "EYLÜL",
      "HAFTA": "1. Hafta:\n08-12 Eylül",
      "SAAT": "4",
      "ÜNİTE": "ORKESTRA TEMEL BİLGİLERİ",
      "BELİRLİ GÜN VE HAFTALAR": "Uluslararası Temiz Hava Günü",
      "KAZANIM": "11.1.1 Orkestranın tarihsel sürecini açıklar.\n11.1.2 Orkestra türlerini ve özelliklerini ayırt eder.\nFarklı büyüklükteki orkestralar ve çalgı toplulukları hakkında bilgi verilir."
    },
    {
      "AY": "EYLÜL",
      "HAFTA": "2. Hafta:\n15-19 Eylül",
      "SAAT": "4",
      "ÜNİTE": "ORKESTRA TEMEL BİLGİLERİ",
      "BELİRLİ GÜN VE HAFTALAR": "İlköğretim Haftası Mevlid-i Nebî Haftası Öğrenciler Günü Gaziler Günü",
      "KAZANIM": "11.1.3 Orkestra çalgılarını ve tınılarını açıklar.\n11.1.4 Ses aralıklarını porte üzerindeki yerlerini verir."
    },
    {
      "AY": "EYLÜL",
      "HAFTA": "3. Hafta:\n22-26 Eylül",
      "SAAT": "4",
      "ÜNİTE": "ORKESTRA TEMEL BİLGİLERİ",
      "KAZANIM": "11.1.5 Orkestradaki çalgı gruplarını açıklar.\n11.1.6 Oturma düzenini açıklar."
    },
    {
      "AY": "EYLÜL",
      "HAFTA": "4. Hafta:\n29 Eylül-03 Ekim",
      "SAAT": "4",
      "ÜNİTE": "ORKESTRADA TEMEL ÇALIŞMALAR",
      "BELİRLİ GÜN VE HAFTALAR": "Disleksi Haftası Dünya Disleksi Günü",
      "KAZANIM": "11.2.1 Orkestra şefinin görevini açıklar.\n11.2.2 Şefin el ve yüz ifadelerinin önemini açıklar."
    },
    {
      "AY": "EKIM",
      "HAFTA": "5. Hafta:\n06-10 Ekim",
      "SAAT": "4",
      "ÜNİTE": "ORKESTRADA TEMEL ÇALIŞMALAR",
      "BELİRLİ GÜN VE HAFTALAR": "Ahilik Kültürü Haftası",
      "KAZANIM": "11.2.3 Dünya çapında tanınmış orkestra şeflerine örnekler verir.\n11.2.4 Orkestral yazım türlerini ayırt eder."
    },
    {
      "AY": "EKIM",
      "HAFTA": "6. Hafta:\n13-17 Ekim",
      "SAAT": "4",
      "ÜNİTE": "ORKESTRADA TEMEL ÇALIŞMALAR",
      "KAZANIM": "11.2.5 Orkestra üyesi olarak kendi partisini takip eder."
    },
    {
      "AY": "EKIM",
      "HAFTA": "7. Hafta:\n20-24 Ekim",
      "SAAT": "4",
      "ÜNİTE": "TOPLU ÇALIŞMA VE ÇALMA UYGULAMALARI",
      "KAZANIM": "11.3.1 Toplu çalışma aşamalarını açıklar.\nUyulması gereken kurallar belirtilir."
    },
    {
      "AY": "EKIM",
      "HAFTA": "8. Hafta:\n27-31 Ekim",
      "SAAT": "4",
      "ÜNİTE": "TOPLU ÇALIŞMA VE ÇALMA UYGULAMALARI",
      "BELİRLİ GÜN VE HAFTALAR": "Cumhuriyet Bayramı",
      "KAZANIM": "11.3.1 Toplu çalışma aşamalarını açıklar.\nUyulması gereken kurallar belirtilir."
    },
    {
      "AY": "KASIM",
      "HAFTA": "9. Hafta:\n03-07 Kasım",
      "SAAT": "4",
      "ÜNİTE": "TOPLU ÇALIŞMA VE ÇALMA UYGULAMALARI",
      "BELİRLİ GÜN VE HAFTALAR": "Kızılay Haftası Organ Bağışı ve Nakli Haftası Lösemili Çocuklar Haftası",
      "KAZANIM": "1. Dönem 1. Sınav 11.3.2 Entonasyon ve ses bütünlüğünün önemini açıklar."
    },
    {
      "AY": "KASIM",
      "HAFTA": "10. Hafta:\n10-14 Kasım",
      "SAAT": "4",
      "ÜNİTE": "1. Dönem Ara Tatili",
      "KONU": "1. Dönem Ara Tatili",
      "BELİRLİ GÜN VE HAFTALAR": "Atatürk Haftası Afet Eğitimi Hazırlık Günü Dünya Diyabet Günü",
      "KAZANIM": "1. Dönem Ara Tatili"
    },
    {
      "AY": "KASIM",
      "HAFTA": "11. Hafta:\n17-21 Kasım",
      "SAAT": "4",
      "ÜNİTE": "TOPLU ÇALIŞMA VE ÇALMA UYGULAMALARI",
      "BELİRLİ GÜN VE HAFTALAR": "Dünya FELSEFE Günü Dünya Çocuk Hakları Günü",
      "KAZANIM": "11.3.2 Entonasyon ve ses bütünlüğünün önemini açıklar."
    },
    {
      "AY": "KASIM",
      "HAFTA": "12. Hafta:\n24-28 Kasım",
      "SAAT": "4",
      "ÜNİTE": "TOPLU ÇALIŞMA VE ÇALMA UYGULAMALARI",
      "BELİRLİ GÜN VE HAFTALAR": "Ağız ve Diş Sağlığı Haftası Öğretmenler Günü",
      "KAZANIM": "11.3.3 Şefe uyumun önemini açıklar."
    },
    {
      "AY": "ARALIK",
      "HAFTA": "13. Hafta:\n01-05 Aralık",
      "SAAT": "4",
      "ÜNİTE": "TOPLU ÇALIŞMA VE ÇALMA UYGULAMALARI",
      "BELİRLİ GÜN VE HAFTALAR": "Dünya Engelliler Günü Dünya Madenciler Günü Türk Kadınına Seçme ve Seçilme Hakkının Verilişi",
      "KAZANIM": "11.3.3 Şefe uyumun önemini açıklar."
    },
    {
      "AY": "ARALIK",
      "HAFTA": "14. Hafta:\n08-12 Aralık",
      "SAAT": "4",
      "ÜNİTE": "TOPLU ÇALIŞMA VE ÇALMA UYGULAMALARI",
      "BELİRLİ GÜN VE HAFTALAR": "Mevlana Haftası İnsan Hakları ve Demokrasi Haftası",
      "KAZANIM": "11.3.4 Çalgısını akort eder."
    },
    {
      "AY": "ARALIK",
      "HAFTA": "15. Hafta:\n15-19 Aralık",
      "SAAT": "4",
      "ÜNİTE": "TOPLU ÇALIŞMA VE ÇALMA UYGULAMALARI",
      "BELİRLİ GÜN VE HAFTALAR": "Tutum Yatırım ve Türk Malları Haftası",
      "KAZANIM": "11.3.4 Çalgısını akort eder."
    },
    {
      "AY": "ARALIK",
      "HAFTA": "16. Hafta:\n22-26 Aralık",
      "SAAT": "4",
      "ÜNİTE": "TOPLU ÇALIŞMA VE ÇALMA UYGULAMALARI",
      "BELİRLİ GÜN VE HAFTALAR": "Mehmet Akif Ersoyu Anma Haftası",
      "KAZANIM": "11.3.5 Toplu çalma uygulamalarını gerçekleştirir.\nDo majör La minör Fa majör Re minör Sol majör Mi minör Si bemol majör Sol minör Re majör Si minör Mi bemol majör Do minör La majör Fa diyez minör tonlarında kadanslar yazılır.\nFarklı harmonik diziler yazılır.\nFarklı tonlarda kadanslarla harmonik uygulamalar yapılır."
    },
    {
      "AY": "ARALIK",
      "HAFTA": "17. Hafta:\n29 Aralık-02 Ocak",
      "SAAT": "4",
      "ÜNİTE": "TOPLU ÇALIŞMA VE ÇALMA UYGULAMALARI",
      "KAZANIM": "11.3.5 Toplu çalma uygulamalarını gerçekleştirir.\nDo majör La minör Fa majör Re minör Sol majör Mi minör Si bemol majör Sol minör Re majör Si minör Mi bemol majör Do minör La majör Fa diyez minör tonlarında kadanslar yazılır.\nFarklı harmonik diziler yazılır.\nFarklı tonlarda kadanslarla harmonik uygulamalar yapılır."
    },
    {
      "AY": "OCAK",
      "HAFTA": "18. Hafta:\n05-09 Ocak",
      "SAAT": "4",
      "ÜNİTE": "TOPLU ÇALIŞMA VE ÇALMA UYGULAMALARI",
      "BELİRLİ GÜN VE HAFTALAR": "Enerji Tasarrufu Haftası",
      "KAZANIM": "1. Dönem 2. Sınav 11.3.6 İki partili eserleri seslendirir.\nDeşifre çalışmaları yapılır.\nDoğru entonasyon tempo ve günlük terimlerle icra edilir."
    },
    {
      "AY": "OCAK",
      "HAFTA": "19. Hafta:\n12-16 Ocak",
      "SAAT": "4",
      "ÜNİTE": "Etkinlik Haftası",
      "KONU": "Etkinlik Haftası",
      "KAZANIM": "Etkinlik Haftası"
    },
    {
      "AY": "OCAK",
      "HAFTA": "20. Hafta:\n19-23 Ocak",
      "SAAT": "4",
      "ÜNİTE": "Yarıyıl Tatili",
      "KONU": "Yarıyıl Tatili",
      "KAZANIM": "Yarıyıl Tatili"
    },
    {
      "AY": "OCAK",
      "HAFTA": "21. Hafta:\n26-30 Ocak",
      "SAAT": "4",
      "ÜNİTE": "Yarıyıl Tatili",
      "KONU": "Yarıyıl Tatili",
      "KAZANIM": "Yarıyıl Tatili"
    },
    {
      "AY": "ŞUBAT",
      "HAFTA": "22. Hafta:\n02-06 ubat",
      "SAAT": "4",
      "ÜNİTE": "TOPLU ÇALIŞMA VE ÇALMA UYGULAMALARI",
      "KAZANIM": "11.3.7 Üç partili eserleri seslendirir.\nDeşifre çalışmaları yapılır.\nDoğru entonasyon tempo ve günlük terimlerle icra edilir."
    },
    {
      "AY": "ŞUBAT",
      "HAFTA": "23. Hafta:\n09-13 ubat",
      "SAAT": "4",
      "ÜNİTE": "TOPLU ÇALIŞMA VE ÇALMA UYGULAMALARI",
      "KAZANIM": "11.3.7 Üç partili eserleri seslendirir.\nDeşifre çalışmaları yapılır.\nDoğru entonasyon tempo ve günlük terimlerle icra edilir."
    },
    {
      "AY": "ŞUBAT",
      "HAFTA": "24. Hafta:\n16-20 ubat",
      "SAAT": "4",
      "ÜNİTE": "TOPLU ÇALIŞMA VE ÇALMA UYGULAMALARI",
      "KAZANIM": "11.3.8 Dört partili eserleri seslendirir.\nDeşifre çalışmaları yapılır.\nDoğru entonasyon tempo ve günlük terimlerle icra edilir."
    },
    {
      "AY": "ŞUBAT",
      "HAFTA": "25. Hafta:\n23-27 ubat",
      "SAAT": "4",
      "ÜNİTE": "TOPLU ÇALIŞMA VE ÇALMA UYGULAMALARI",
      "BELİRLİ GÜN VE HAFTALAR": "Vergi Haftası Yeşilay Haftası",
      "KAZANIM": "11.3.8 Dört partili eserleri seslendirir.\nDeşifre çalışmaları yapılır.\nDoğru entonasyon tempo ve günlük terimlerle icra edilir."
    },
    {
      "AY": "MART",
      "HAFTA": "26. Hafta:\n02-06 Mart",
      "SAAT": "4",
      "ÜNİTE": "TOPLU ÇALIŞMA VE ÇALMA UYGULAMALARI",
      "BELİRLİ GÜN VE HAFTALAR": "Girişimcilik Haftası",
      "KAZANIM": "11.3.9 Dörtten fazla partili eserleri seslendirir.\nDeşifre çalışmaları yapılır.\nDoğru entonasyon tempo ve günlük terimlerle icra edilir."
    },
    {
      "AY": "MART",
      "HAFTA": "27. Hafta:\n09-13 Mart",
      "SAAT": "4",
      "ÜNİTE": "TOPLU ÇALIŞMA VE ÇALMA UYGULAMALARI",
      "BELİRLİ GÜN VE HAFTALAR": "Bilim ve Teknoloji Haftası İstiklâl Marşının Kabulü ve Mehmet Akif Ersoyu Anma Günü",
      "KAZANIM": "11.3.9 Dörtten fazla partili eserleri seslendirir.\nDeşifre çalışmaları yapılır.\nDoğru entonasyon tempo ve günlük terimlerle icra edilir."
    },
    {
      "AY": "MART",
      "HAFTA": "28. Hafta:\n16-20 Mart",
      "SAAT": "4",
      "ÜNİTE": "2. Dönem Ara Tatili",
      "KONU": "2. Dönem Ara Tatili",
      "BELİRLİ GÜN VE HAFTALAR": "Tüketiciyi Koruma Haftası Türk Dünyası ve Toplulukları Haftası",
      "KAZANIM": "2. Dönem Ara Tatili"
    },
    {
      "AY": "MART",
      "HAFTA": "29. Hafta:\n23-27 Mart",
      "SAAT": "4",
      "ÜNİTE": "ORKESTRADA KONSER AŞAMALARI",
      "BELİRLİ GÜN VE HAFTALAR": "Orman Haftası Dünya Tiyatrolar Günü",
      "KAZANIM": "11.4.1 Konser hazırlık aşamalarını açıklar.\nBireysel ve grup çalışma aşamaları belirtilir."
    },
    {
      "AY": "MART",
      "HAFTA": "30. Hafta:\n30 Mart-03 Nisan",
      "SAAT": "4",
      "ÜNİTE": "ORKESTRADA KONSER AŞAMALARI",
      "BELİRLİ GÜN VE HAFTALAR": "Kütüphaneler Haftası Kanser Haftası Dünya Otizm Farkındalık Günü",
      "KAZANIM": "11.4.1 Konser hazırlık aşamalarını açıklar.\nBireysel ve grup çalışma aşamaları belirtilir."
    },
    {
      "AY": "NISAN",
      "HAFTA": "31. Hafta:\n06-10 Nisan",
      "SAAT": "4",
      "ÜNİTE": "ORKESTRADA KONSER AŞAMALARI",
      "BELİRLİ GÜN VE HAFTALAR": "Kanser Haftası Dünya Sağlık GününDünya Sağlık Haftası Kişisel Verileri Koruma Günü",
      "KAZANIM": "2. Dönem 1. Sınav 11.4.1 Konser hazırlık aşamalarını açıklar.\nBireysel ve grup çalışma aşamaları belirtilir."
    },
    {
      "AY": "NISAN",
      "HAFTA": "32. Hafta:\n13-17 Nisan",
      "SAAT": "4",
      "ÜNİTE": "ORKESTRADA KONSER AŞAMALARI",
      "BELİRLİ GÜN VE HAFTALAR": "Turizm Haftası",
      "KAZANIM": "11.4.2 Konser performansını gerçekleştirir.\nOrkestra grup çalışma aşamaları belirtilir.\nKonser provalarına dayalı icra yapılır."
    },
    {
      "AY": "NISAN",
      "HAFTA": "33. Hafta:\n20-24 Nisan",
      "SAAT": "4",
      "ÜNİTE": "ORKESTRADA KONSER AŞAMALARI",
      "BELİRLİ GÜN VE HAFTALAR": "Ulusal Egemenlik ve Çocuk Bayramı",
      "KAZANIM": "11.4.2 Konser performansını gerçekleştirir.\nOrkestra grup çalışma aşamaları belirtilir.\nKonser provalarına dayalı icra yapılır."
    },
    {
      "AY": "NISAN",
      "HAFTA": "34. Hafta:\n27 Nisan-01 Mayıs",
      "SAAT": "4",
      "ÜNİTE": "ORKESTRADA KONSER AŞAMALARI",
      "BELİRLİ GÜN VE HAFTALAR": "Kûtül Amâre Zaferi",
      "KAZANIM": "11.4.2 Konser performansını gerçekleştirir.\nOrkestra grup çalışma aşamaları belirtilir.\nKonser provalarına dayalı icra yapılır."
    },
    {
      "AY": "MAYIS",
      "HAFTA": "35. Hafta:\n04-08 Mayıs",
      "SAAT": "4",
      "ÜNİTE": "ORKESTRADA KONSER AŞAMALARI",
      "BELİRLİ GÜN VE HAFTALAR": "Bilişim Haftası Trafik ve İlkyardım Haftası İş Sağlığı ve Güvenliği Haftası",
      "KAZANIM": "11.4.3 Konser öncesi hazırlık sürecini uygular."
    },
    {
      "AY": "MAYIS",
      "HAFTA": "36. Hafta:\n11-15 Mayıs",
      "SAAT": "4",
      "ÜNİTE": "ORKESTRADA KONSER AŞAMALARI",
      "BELİRLİ GÜN VE HAFTALAR": "Engelliler Haftası Vakıflar Haftası",
      "KAZANIM": "11.4.3 Konser öncesi hazırlık sürecini uygular."
    },
    {
      "AY": "MAYIS",
      "HAFTA": "37. Hafta:\n18-22 Mayıs",
      "SAAT": "4",
      "ÜNİTE": "ORKESTRADA KONSER AŞAMALARI",
      "BELİRLİ GÜN VE HAFTALAR": "Müzeler Haftası Atatürkü Anma ve Gençlik ve Spor Bayramı",
      "KAZANIM": "11.4.3 Konser öncesi hazırlık sürecini uygular."
    },
    {
      "AY": "MAYIS",
      "HAFTA": "38. Hafta:\n25-29 Mayıs",
      "SAAT": "4",
      "ÜNİTE": "ORKESTRADA KONSER AŞAMALARI",
      "BELİRLİ GÜN VE HAFTALAR": "Etik Günü İstanbulun Fethi",
      "KAZANIM": "11.4.4 Konser sırasında performans gösterir."
    },
    {
      "AY": "HAZIRAN",
      "HAFTA": "39. Hafta:\n01-05 Haziran",
      "SAAT": "4",
      "ÜNİTE": "ORKESTRADA KONSER AŞAMALARI",
      "BELİRLİ GÜN VE HAFTALAR": "Etik Günü Hayat Boyu Öğrenme Haftası",
      "KAZANIM": "2. Dönem 2. Sınav 11.4.4 Konser sırasında performans gösterir."
    },
    {
      "AY": "HAZIRAN",
      "HAFTA": "40. Hafta:\n08-12 Haziran",
      "SAAT": "4",
      "ÜNİTE": "ORKESTRADA KONSER AŞAMALARI",
      "BELİRLİ GÜN VE HAFTALAR": "Etik Günü Çevre ve İklim Değişikliği Haftası",
      "KAZANIM": "11.4.4 Konser sırasında performans gösterir."
    },
    {
      "AY": "HAZIRAN",
      "HAFTA": "41. Hafta:\n15-19 Haziran",
      "SAAT": "4",
      "ÜNİTE": "Genel Tekrar",
      "KONU": "Genel Tekrar",
      "BELİRLİ GÜN VE HAFTALAR": "Etik Günü",
      "KAZANIM": "Genel Tekrar"
    },
    {
      "AY": "HAZIRAN",
      "HAFTA": "42. Hafta:\n22-26 Haziran",
      "SAAT": "4",
      "ÜNİTE": "Etkinlik Haftası",
      "KONU": "Etkinlik Haftası",
      "BELİRLİ GÜN VE HAFTALAR": "Etik Günü",
      "KAZANIM": "Etkinlik Haftası"
    }
  ]
}