{
  "sinif": "12",
  "ders": "HDROTERAP",
  "plan": [
    {
      "AY": "EYLÜL",
      "HAFTA": "1. Hafta:\n08-12 Eylül",
      "SAAT": "3",
      "KONU": "ÖĞRENME BİRİMİHİDROTERAPİ \n1. HİDROTERAPİ KAVRAMI\n1.1.\tHidroterapi",
      "BELİRLİ GÜN VE HAFTALAR": "Uluslararası Temiz Hava Günü"
    },
    {
      "AY": "EYLÜL",
      "HAFTA": "2. Hafta:\n15-19 Eylül",
      "SAAT": "3",
      "KONU": "1.2.\tHidroterapi uygulamaları",
      "BELİRLİ GÜN VE HAFTALAR": "İlköğretim Haftası Mevlid-i Nebî Haftası Öğrenciler Günü Gaziler Günü"
    },
    {
      "AY": "EYLÜL",
      "HAFTA": "3. Hafta:\n22-26 Eylül",
      "SAAT": "3",
      "KONU": "1.3.\tHidroterapi kullanım alanları"
    },
    {
      "AY": "EYLÜL",
      "HAFTA": "4. Hafta:\n29 Eylül-03 Ekim",
      "SAAT": "3",
      "KONU": "2.HİDROTERAPİ TEDAVİ UYGULAMALARI\n2.1.\tHidroterapi tedavi yöntemleri",
      "BELİRLİ GÜN VE HAFTALAR": "Disleksi Haftası Dünya Disleksi Günü"
    },
    {
      "AY": "EKIM",
      "HAFTA": "5. Hafta:\n06-10 Ekim",
      "SAAT": "3",
      "KONU": "2.2.\tHidroterapide kullanılan araç gereç ve ekipmanlar",
      "BELİRLİ GÜN VE HAFTALAR": "Ahilik Kültürü Haftası"
    },
    {
      "AY": "EKIM",
      "HAFTA": "6. Hafta:\n13-17 Ekim",
      "SAAT": "3",
      "KONU": "2.2.\tHidroterapide kullanılan araç gereç ve ekipmanlar"
    },
    {
      "AY": "EKIM",
      "HAFTA": "7. Hafta:\n20-24 Ekim",
      "SAAT": "3",
      "KONU": "ÖĞRENME BİRİMİ OTURMA BANYOSU UYGULAMALARI\n1.OTURMA BANYOSUNUN ÖZELLİKLERİ\n1.1.\tOturma banyosunda kullanılan araç gereçler"
    },
    {
      "AY": "EKIM",
      "HAFTA": "8. Hafta:\n27-31 Ekim",
      "SAAT": "3",
      "KONU": "1.2.\tOturma banyosu uygulamasının etki mekanizması  \n\n1.Dönem 1.Sınav",
      "BELİRLİ GÜN VE HAFTALAR": "Cumhuriyet Bayramı"
    },
    {
      "AY": "KASIM",
      "HAFTA": "9. Hafta:\n03-07 Kasım",
      "SAAT": "3",
      "KONU": "2.OTURMA BANYOSU ENDİKASYONU\n2.1.\tOturma banyosunun tedavide kullanıldığı sağlık problemleri",
      "BELİRLİ GÜN VE HAFTALAR": "Kızılay Haftası Organ Bağışı ve Nakli Haftası Lösemili Çocuklar Haftası"
    },
    {
      "AY": "KASIM",
      "HAFTA": "10. Hafta:\n10-14 Kasım",
      "SAAT": "3",
      "ÜNİTE": "1. Dönem Ara Tatili",
      "KONU": "1. Dönem Ara Tatili",
      "BELİRLİ GÜN VE HAFTALAR": "Atatürk Haftası Afet Eğitimi Hazırlık Günü Dünya Diyabet Günü"
    },
    {
      "AY": "KASIM",
      "HAFTA": "11. Hafta:\n17-21 Kasım",
      "SAAT": "3",
      "KONU": "2.2.\tOturma banyosu uygulamasının kontrendikasyonları",
      "BELİRLİ GÜN VE HAFTALAR": "Dünya FELSEFE Günü Dünya Çocuk Hakları Günü"
    },
    {
      "AY": "KASIM",
      "HAFTA": "12. Hafta:\n24-28 Kasım",
      "SAAT": "3",
      "KONU": "3.OTURMA BANYOSU  UYGULAMASI\n3.1.\tOturma banyosu uygulamasında dikkat edilecek hususlar",
      "BELİRLİ GÜN VE HAFTALAR": "Ağız ve Diş Sağlığı Haftası Öğretmenler Günü"
    },
    {
      "AY": "ARALIK",
      "HAFTA": "13. Hafta:\n01-05 Aralık",
      "SAAT": "3",
      "KONU": "3.2.\tOturma banyosunda kullanılacak araç-gereçlerin hazırlanması",
      "BELİRLİ GÜN VE HAFTALAR": "Dünya Engelliler Günü Dünya Madenciler Günü Türk Kadınına Seçme ve Seçilme Hakkının Verilişi"
    },
    {
      "AY": "ARALIK",
      "HAFTA": "14. Hafta:\n08-12 Aralık",
      "SAAT": "3",
      "KONU": "3.3.\tOturma banyosu uygulamasında hijyen kurallarına uyarak sağlık personeline yardım etme",
      "BELİRLİ GÜN VE HAFTALAR": "Mevlana Haftası İnsan Hakları ve Demokrasi Haftası"
    },
    {
      "AY": "ARALIK",
      "HAFTA": "15. Hafta:\n15-19 Aralık",
      "SAAT": "3",
      "KONU": "ÖĞRENME BİRİMİ BUHAR BANYOSU UYGULAMALARI\n1.BUHAR BANYOSUNUN ÖZELLİKLERİ\n1.1.\tBuhar banyosu uygulamasının etki mekanizması",
      "BELİRLİ GÜN VE HAFTALAR": "Tutum Yatırım ve Türk Malları Haftası"
    },
    {
      "AY": "ARALIK",
      "HAFTA": "16. Hafta:\n22-26 Aralık",
      "SAAT": "3",
      "KONU": "1.2.\tBuhar banyosunun tedavide kullanıldığı sağlık problemleri",
      "BELİRLİ GÜN VE HAFTALAR": "Mehmet Akif Ersoyu Anma Haftası"
    },
    {
      "AY": "ARALIK",
      "HAFTA": "17. Hafta:\n29 Aralık-02 Ocak",
      "SAAT": "3",
      "KONU": "2.BUHAR BANYOSU UYGULAMASI \n2.1.\tBuhar banyosunda kullanılan araç gereçler   \n1.Dönem 2.Sınav"
    },
    {
      "AY": "OCAK",
      "HAFTA": "18. Hafta:\n05-09 Ocak",
      "SAAT": "3",
      "KONU": "2.2.\tBuhar banyosu uygulaması işlem basamakları",
      "BELİRLİ GÜN VE HAFTALAR": "Enerji Tasarrufu Haftası"
    },
    {
      "AY": "OCAK",
      "HAFTA": "19. Hafta:\n12-16 Ocak",
      "SAAT": "3",
      "ÜNİTE": "Etkinlik Haftası",
      "KONU": "Etkinlik Haftası"
    },
    {
      "AY": "OCAK",
      "HAFTA": "20. Hafta:\n19-23 Ocak",
      "SAAT": "3",
      "ÜNİTE": "Yarıyıl Tatili",
      "KONU": "Yarıyıl Tatili"
    },
    {
      "AY": "OCAK",
      "HAFTA": "21. Hafta:\n26-30 Ocak",
      "SAAT": "3",
      "ÜNİTE": "Yarıyıl Tatili",
      "KONU": "Yarıyıl Tatili"
    },
    {
      "AY": "ŞUBAT",
      "HAFTA": "22. Hafta:\n02-06 ubat",
      "SAAT": "3",
      "KONU": "2.2.\tBuhar banyosu uygulaması işlem basamakları"
    },
    {
      "AY": "ŞUBAT",
      "HAFTA": "23. Hafta:\n09-13 ubat",
      "SAAT": "3",
      "KONU": "ÖĞRENME BİRİMİ İRRİGASYON UYGULAMALARI\n1.İRRİGASYON ÖZELLİKLERİ\n1.1.\tİrrigasyon uygulaması türleri"
    },
    {
      "AY": "ŞUBAT",
      "HAFTA": "24. Hafta:\n16-20 ubat",
      "SAAT": "3",
      "KONU": "1.2.\tİrrigasyon uygulamasının kullanıldığı sağlık problemleri"
    },
    {
      "AY": "ŞUBAT",
      "HAFTA": "25. Hafta:\n23-27 ubat",
      "SAAT": "3",
      "KONU": "2.İRRİGASYON UYGULAMASI\n2.1.\tİrrigasyon uygulamalarında kullanılan araç-gereçler",
      "BELİRLİ GÜN VE HAFTALAR": "Vergi Haftası Yeşilay Haftası"
    },
    {
      "AY": "MART",
      "HAFTA": "26. Hafta:\n02-06 Mart",
      "SAAT": "3",
      "KONU": "2.2.\tİrrigasyon uygulaması işlem basamakları",
      "BELİRLİ GÜN VE HAFTALAR": "Girişimcilik Haftası"
    },
    {
      "AY": "MART",
      "HAFTA": "27. Hafta:\n09-13 Mart",
      "SAAT": "3",
      "KONU": "2.2.\tİrrigasyon uygulaması işlem basamakları",
      "BELİRLİ GÜN VE HAFTALAR": "Bilim ve Teknoloji Haftası İstiklâl Marşının Kabulü ve Mehmet Akif Ersoyu Anma Günü"
    },
    {
      "AY": "MART",
      "HAFTA": "28. Hafta:\n16-20 Mart",
      "SAAT": "3",
      "ÜNİTE": "2. Dönem Ara Tatili",
      "KONU": "2. Dönem Ara Tatili",
      "BELİRLİ GÜN VE HAFTALAR": "Tüketiciyi Koruma Haftası Türk Dünyası ve Toplulukları Haftası"
    },
    {
      "AY": "MART",
      "HAFTA": "29. Hafta:\n23-27 Mart",
      "SAAT": "3",
      "KONU": "ÖĞRENME BİRİMİ SICAK-SOĞUK KOMPRES UYGULAMALARI\n1.SICAK SOĞUK UYGULAMALARIN ÖZELLİKLERİ\n1.1.\tSıcak-soğuk uygulamalarda kullanılan araç gereçler",
      "BELİRLİ GÜN VE HAFTALAR": "Orman Haftası Dünya Tiyatrolar Günü"
    },
    {
      "AY": "MART",
      "HAFTA": "30. Hafta:\n30 Mart-03 Nisan",
      "SAAT": "3",
      "KONU": "1.2.\tSıcak-soğuk uygulamalarının tedavide kullanımı \n\n2.Dönem 1.Sınav",
      "BELİRLİ GÜN VE HAFTALAR": "Kütüphaneler Haftası Kanser Haftası Dünya Otizm Farkındalık Günü"
    },
    {
      "AY": "NISAN",
      "HAFTA": "31. Hafta:\n06-10 Nisan",
      "SAAT": "3",
      "KONU": "1.2.\tSıcak-soğuk uygulamalarının tedavide kullanımı",
      "BELİRLİ GÜN VE HAFTALAR": "Kanser Haftası Dünya Sağlık GününDünya Sağlık Haftası Kişisel Verileri Koruma Günü"
    },
    {
      "AY": "NISAN",
      "HAFTA": "32. Hafta:\n13-17 Nisan",
      "SAAT": "3",
      "KONU": "2.KURU ISI NEMLİ ISI YAŞ ISI UYGULAMALARI\n2.1.\tSıcak uygulamaların yöntemleri",
      "BELİRLİ GÜN VE HAFTALAR": "Turizm Haftası"
    },
    {
      "AY": "NISAN",
      "HAFTA": "33. Hafta:\n20-24 Nisan",
      "SAAT": "3",
      "KONU": "2.2.\tSıcak uygulamalarının tedavide kullanımı",
      "BELİRLİ GÜN VE HAFTALAR": "Ulusal Egemenlik ve Çocuk Bayramı"
    },
    {
      "AY": "NISAN",
      "HAFTA": "34. Hafta:\n27 Nisan-01 Mayıs",
      "SAAT": "3",
      "KONU": "2.2.\tSıcak uygulamalarının tedavide kullanımı",
      "BELİRLİ GÜN VE HAFTALAR": "Kûtül Amâre Zaferi"
    },
    {
      "AY": "MAYIS",
      "HAFTA": "35. Hafta:\n04-08 Mayıs",
      "SAAT": "3",
      "KONU": "3.SOĞUK KOMPRES BUZ UYGULAMALARI\n3.1.\tSoğuk uygulamaların yöntemleri",
      "BELİRLİ GÜN VE HAFTALAR": "Bilişim Haftası Trafik ve İlkyardım Haftası İş Sağlığı ve Güvenliği Haftası"
    },
    {
      "AY": "MAYIS",
      "HAFTA": "36. Hafta:\n11-15 Mayıs",
      "SAAT": "3",
      "KONU": "3.2.\tSoğuk uygulamalarının tedavide kullanımı",
      "BELİRLİ GÜN VE HAFTALAR": "Engelliler Haftası Vakıflar Haftası"
    },
    {
      "AY": "MAYIS",
      "HAFTA": "37. Hafta:\n18-22 Mayıs",
      "SAAT": "3",
      "KONU": "ÖĞRENME BİRİMİ HAVUZ İÇİ EGZERSİZ UYGULAMALARI\n1.HAVUZ İÇİ EGZERSİZ UYGULAMA ÖZELLİKLERİ\n1.1.\tHavuz içi egzersiz uygulamalarında kullanılan araç-gereçler",
      "BELİRLİ GÜN VE HAFTALAR": "Müzeler Haftası Atatürkü Anma ve Gençlik ve Spor Bayramı"
    },
    {
      "AY": "MAYIS",
      "HAFTA": "38. Hafta:\n25-29 Mayıs",
      "SAAT": "3",
      "KONU": "1.2.\tHavuz içi egzersiz uygulamalarının sağlık alanında kullanımı",
      "BELİRLİ GÜN VE HAFTALAR": "Etik Günü İstanbulun Fethi"
    },
    {
      "AY": "HAZIRAN",
      "HAFTA": "39. Hafta:\n01-05 Haziran",
      "SAAT": "3",
      "KONU": "2.HAVUZ İÇİ EGZERSİZ UYGULAMASI\n2.1.\tHavuz içi egzersiz uygulamaları hakkında hastayı bilgilendirme",
      "BELİRLİ GÜN VE HAFTALAR": "Etik Günü Hayat Boyu Öğrenme Haftası"
    },
    {
      "AY": "HAZIRAN",
      "HAFTA": "40. Hafta:\n08-12 Haziran",
      "SAAT": "3",
      "KONU": "2.2.\tHavuz içi egzersiz uygulamaları  \n2.Dönem 2.Sınav",
      "BELİRLİ GÜN VE HAFTALAR": "Etik Günü Çevre ve İklim Değişikliği Haftası"
    },
    {
      "AY": "HAZIRAN",
      "HAFTA": "41. Hafta:\n15-19 Haziran",
      "SAAT": "3",
      "KONU": "2.2.\tHavuz içi egzersiz uygulamaları",
      "BELİRLİ GÜN VE HAFTALAR": "Etik Günü"
    },
    {
      "AY": "HAZIRAN",
      "HAFTA": "42. Hafta:\n22-26 Haziran",
      "SAAT": "3",
      "ÜNİTE": "Etkinlik Haftası",
      "KONU": "Etkinlik Haftası",
      "BELİRLİ GÜN VE HAFTALAR": "Etik Günü"
    }
  ]
}