{
  "sinif": "9",
  "ders": "ETKL ILETSM",
  "plan": [
    {
      "ÜNİTE": "İletişim",
      "AY": "EYLÜL",
      "HAFTA": "1. Hafta:\n08-12 Eylül",
      "SAAT": "3",
      "KONU": "1.   İletişim",
      "BELİRLİ GÜN VE HAFTALAR": "Uluslararası Temiz Hava Günü",
      "KAZANIM": "İletişim ile ilgili kavramları açıklar."
    },
    {
      "ÜNİTE": "İletişim",
      "AY": "EYLÜL",
      "HAFTA": "2. Hafta:\n15-19 Eylül",
      "SAAT": "3",
      "KONU": "2.   İletişim Süreci ve Türleri",
      "BELİRLİ GÜN VE HAFTALAR": "İlköğretim Haftası Mevlid-i Nebî Haftası Öğrenciler Günü Gaziler Günü",
      "KAZANIM": "İletişim sürecini ve türlerini açıklar.\nKodlamakod açma kaynak ileti alıcı geri bildirim gürültü ortambağlam kavramaları açıklanır.\n     Yönüne göre tek ve çift iletişim açıklanır."
    },
    {
      "ÜNİTE": "İletişim",
      "AY": "EYLÜL",
      "HAFTA": "3. Hafta:\n22-26 Eylül",
      "SAAT": "3",
      "KONU": "2.   İletişim Süreci ve Türleri",
      "KAZANIM": "İletişim sürecini ve türlerini açıklar.\nKod sistemine göre sözlü sözsüz yazılı iletişim açıklanır.\n      İlişki sistemine göre kişi-içi içsel kişilerarası grup iletişimi örgütsel kitle iletişimi iletişim açıklanır."
    },
    {
      "ÜNİTE": "İletişim",
      "AY": "EYLÜL",
      "HAFTA": "4. Hafta:\n29 Eylül-03 Ekim",
      "SAAT": "3",
      "KONU": "2.   İletişim Süreci ve Türleri",
      "BELİRLİ GÜN VE HAFTALAR": "Disleksi Haftası Dünya Disleksi Günü",
      "KAZANIM": "İletişim sürecini ve türlerini açıklar.\nBirey konumuna göre yatay dikey iletişim açıklanır.\n     Zaman ve mekan boyutuna göre  yüz yüze uzaktan iletişim açıklanır."
    },
    {
      "ÜNİTE": "Empati ve Dinleme",
      "AY": "EKIM",
      "HAFTA": "5. Hafta:\n06-10 Ekim",
      "SAAT": "3",
      "KONU": "1.   Algı ve İletişim",
      "BELİRLİ GÜN VE HAFTALAR": "Ahilik Kültürü Haftası",
      "KAZANIM": "Algının iletişim sürecindeki önemini örneklerle açıklar.\nAlgı kavramı açıklanır.\n     Algının iletişime etkisi örneklerle açıklanır.\n     Algıya etki eden unsurlar açıklanır."
    },
    {
      "ÜNİTE": "Empati ve Dinleme",
      "AY": "EKIM",
      "HAFTA": "6. Hafta:\n13-17 Ekim",
      "SAAT": "3",
      "KONU": "4.   Etkin Dinleme",
      "KAZANIM": "İletişim sürecinde etkin dinleme tekniklerini kullanır.\nEdilgin dinleme yöntemi örneklerle açıklanır."
    },
    {
      "ÜNİTE": "Empati ve Dinleme",
      "AY": "EKIM",
      "HAFTA": "7. Hafta:\n20-24 Ekim",
      "SAAT": "3",
      "KONU": "3.   Dinleme ve İletişim",
      "KAZANIM": "Dinlemenin iletişim sürecindeki yerini değerlendirir.\nDinleme kavramı açıklanır."
    },
    {
      "ÜNİTE": "Empati ve Dinleme",
      "AY": "EKIM",
      "HAFTA": "8. Hafta:\n27-31 Ekim",
      "SAAT": "3",
      "KONU": "2.   Empati ve İletişim",
      "BELİRLİ GÜN VE HAFTALAR": "Cumhuriyet Bayramı",
      "KAZANIM": "Empatinin iletişim sürecindeki önemini örneklerle açıklar.\nEmpati kavramı açıklanır.\n     Empatinin iletişimdeki önemi örneklerle açıklanır."
    },
    {
      "ÜNİTE": "Empati ve Dinleme",
      "AY": "KASIM",
      "HAFTA": "9. Hafta:\n03-07 Kasım",
      "SAAT": "3",
      "KONU": "4.   Etkin Dinleme",
      "BELİRLİ GÜN VE HAFTALAR": "Kızılay Haftası Organ Bağışı ve Nakli Haftası Lösemili Çocuklar Haftası",
      "KAZANIM": "1. Dönem 1. Sınav  İletişim sürecinde etkin dinleme tekniklerini kullanır.\nİletişim engelleri örneklerle açıklanır."
    },
    {
      "ÜNİTE": "1. Dönem Ara Tatili",
      "AY": "KASIM",
      "HAFTA": "10. Hafta:\n10-14 Kasım",
      "SAAT": "3",
      "KONU": "1. Dönem Ara Tatili",
      "BELİRLİ GÜN VE HAFTALAR": "Atatürk Haftası Afet Eğitimi Hazırlık Günü Dünya Diyabet Günü",
      "KAZANIM": "1. Dönem Ara Tatili"
    },
    {
      "ÜNİTE": "Empati ve Dinleme",
      "AY": "KASIM",
      "HAFTA": "11. Hafta:\n17-21 Kasım",
      "SAAT": "3",
      "KONU": "3.   Dinleme ve İletişim",
      "BELİRLİ GÜN VE HAFTALAR": "Dünya FELSEFE Günü Dünya Çocuk Hakları Günü",
      "KAZANIM": "Dinlemenin iletişim sürecindeki yerini değerlendirir.\nDinlemenin iletişim sürecindeki önemi örneklerle açıklanır."
    },
    {
      "ÜNİTE": "Empati ve Dinleme",
      "AY": "KASIM",
      "HAFTA": "12. Hafta:\n24-28 Kasım",
      "SAAT": "3",
      "KONU": "3.   Dinleme ve İletişim",
      "BELİRLİ GÜN VE HAFTALAR": "Ağız ve Diş Sağlığı Haftası Öğretmenler Günü",
      "KAZANIM": "Dinlemenin iletişim sürecindeki yerini değerlendirir.\nDinleme engelleri örneklerle açıklanır."
    },
    {
      "ÜNİTE": "Empati ve Dinleme",
      "AY": "ARALIK",
      "HAFTA": "13. Hafta:\n01-05 Aralık",
      "SAAT": "3",
      "KONU": "4.   Etkin Dinleme",
      "BELİRLİ GÜN VE HAFTALAR": "Dünya Engelliler Günü Dünya Madenciler Günü Türk Kadınına Seçme ve Seçilme Hakkının Verilişi",
      "KAZANIM": "İletişim sürecinde etkin dinleme tekniklerini kullanır.\nKapı aralayıcılar örneklerle açıklanır."
    },
    {
      "ÜNİTE": "Empati ve Dinleme",
      "AY": "ARALIK",
      "HAFTA": "14. Hafta:\n08-12 Aralık",
      "SAAT": "3",
      "KONU": "3.   Dinleme ve İletişim",
      "BELİRLİ GÜN VE HAFTALAR": "Mevlana Haftası İnsan Hakları ve Demokrasi Haftası",
      "KAZANIM": "Dinlemenin iletişim sürecindeki yerini değerlendirir.\nEtkisiz dinleme türleri iletişime etkileri açısından değerlendirilir."
    },
    {
      "ÜNİTE": "Empati ve Dinleme",
      "AY": "ARALIK",
      "HAFTA": "15. Hafta:\n15-19 Aralık",
      "SAAT": "3",
      "KONU": "4.   Etkin Dinleme",
      "BELİRLİ GÜN VE HAFTALAR": "Tutum Yatırım ve Türk Malları Haftası",
      "KAZANIM": "İletişim sürecinde etkin dinleme tekniklerini kullanır.\nEtkin dinleme kullanımı örneklerle açıklanır."
    },
    {
      "ÜNİTE": "Empati ve Dinleme",
      "AY": "ARALIK",
      "HAFTA": "16. Hafta:\n22-26 Aralık",
      "SAAT": "3",
      "KONU": "4.   Etkin Dinleme",
      "BELİRLİ GÜN VE HAFTALAR": "Mehmet Akif Ersoyu Anma Haftası",
      "KAZANIM": "İletişim sürecinde etkin dinleme tekniklerini kullanır.\nEtkin dinleme yönteminin uygulanmasında dikkat edilmesi gereken hususlar açıklanır."
    },
    {
      "ÜNİTE": "Empati ve Dinleme",
      "AY": "ARALIK",
      "HAFTA": "17. Hafta:\n29 Aralık-02 Ocak",
      "SAAT": "3",
      "KONU": "3.   Dinleme ve İletişim",
      "KAZANIM": "Dinlemenin iletişim sürecindeki yerini değerlendirir.\nEtkisiz dinleme türleri iletişime etkileri açısından değerlendirilir."
    },
    {
      "ÜNİTE": "Kendini İfade Etme",
      "AY": "OCAK",
      "HAFTA": "18. Hafta:\n05-09 Ocak",
      "SAAT": "3",
      "KONU": "1.   Konuşma ve İletişim",
      "BELİRLİ GÜN VE HAFTALAR": "Enerji Tasarrufu Haftası",
      "KAZANIM": "1. Dönem 2. Sınav  Konuşmanın iletişim sürecindeki önemini örneklerle açıklar."
    },
    {
      "ÜNİTE": "Etkinlik Haftası",
      "AY": "OCAK",
      "HAFTA": "19. Hafta:\n12-16 Ocak",
      "SAAT": "3",
      "KONU": "Etkinlik Haftası",
      "KAZANIM": "Etkinlik Haftası"
    },
    {
      "ÜNİTE": "Yarıyıl Tatili",
      "AY": "OCAK",
      "HAFTA": "20. Hafta:\n19-23 Ocak",
      "SAAT": "3",
      "KONU": "Yarıyıl Tatili",
      "KAZANIM": "Yarıyıl Tatili"
    },
    {
      "ÜNİTE": "Yarıyıl Tatili",
      "AY": "OCAK",
      "HAFTA": "21. Hafta:\n26-30 Ocak",
      "SAAT": "3",
      "KONU": "Yarıyıl Tatili",
      "KAZANIM": "Yarıyıl Tatili"
    },
    {
      "ÜNİTE": "Kendini İfade Etme",
      "AY": "ŞUBAT",
      "HAFTA": "22. Hafta:\n02-06 ubat",
      "SAAT": "3",
      "KONU": "1.   Konuşma ve İletişim",
      "KAZANIM": "Konuşmanın iletişim sürecindeki önemini örneklerle açıklar."
    },
    {
      "ÜNİTE": "Kendini İfade Etme",
      "AY": "ŞUBAT",
      "HAFTA": "23. Hafta:\n09-13 ubat",
      "SAAT": "3",
      "KONU": "2.   Sen Dili",
      "KAZANIM": "Sen dilini kullanmanın iletişime olan etkilerini örnekler ile açıklar."
    },
    {
      "ÜNİTE": "Kendini İfade Etme",
      "AY": "ŞUBAT",
      "HAFTA": "24. Hafta:\n16-20 ubat",
      "SAAT": "3",
      "KONU": "1.   Konuşma ve İletişim",
      "KAZANIM": "Konuşmanın iletişim sürecindeki önemini örneklerle açıklar."
    },
    {
      "ÜNİTE": "Kendini İfade Etme",
      "AY": "ŞUBAT",
      "HAFTA": "25. Hafta:\n23-27 ubat",
      "SAAT": "3",
      "KONU": "3.   Ben Dili",
      "BELİRLİ GÜN VE HAFTALAR": "Vergi Haftası Yeşilay Haftası",
      "KAZANIM": "İletişimde ben dili kullanımını örnekler ile açıklar."
    },
    {
      "ÜNİTE": "Kendini İfade Etme",
      "AY": "MART",
      "HAFTA": "26. Hafta:\n02-06 Mart",
      "SAAT": "3",
      "KONU": "1.   Konuşma ve İletişim",
      "BELİRLİ GÜN VE HAFTALAR": "Girişimcilik Haftası",
      "KAZANIM": "Konuşmanın iletişim sürecindeki önemini örneklerle açıklar."
    },
    {
      "ÜNİTE": "Kendini İfade Etme",
      "AY": "MART",
      "HAFTA": "27. Hafta:\n09-13 Mart",
      "SAAT": "3",
      "KONU": "4.   Olumsuz İfadeler",
      "BELİRLİ GÜN VE HAFTALAR": "Bilim ve Teknoloji Haftası İstiklâl Marşının Kabulü ve Mehmet Akif Ersoyu Anma Günü",
      "KAZANIM": "İletişimde olumsuz ifadeler kullanmanın sonucunu tartışır."
    },
    {
      "ÜNİTE": "2. Dönem Ara Tatili",
      "AY": "MART",
      "HAFTA": "28. Hafta:\n16-20 Mart",
      "SAAT": "3",
      "KONU": "2. Dönem Ara Tatili",
      "BELİRLİ GÜN VE HAFTALAR": "Tüketiciyi Koruma Haftası Türk Dünyası ve Toplulukları Haftası",
      "KAZANIM": "2. Dönem Ara Tatili"
    },
    {
      "ÜNİTE": "Kendini İfade Etme",
      "AY": "MART",
      "HAFTA": "29. Hafta:\n23-27 Mart",
      "SAAT": "3",
      "KONU": "1.   Konuşma ve İletişim",
      "BELİRLİ GÜN VE HAFTALAR": "Orman Haftası Dünya Tiyatrolar Günü",
      "KAZANIM": "Konuşmanın iletişim sürecindeki önemini örneklerle açıklar."
    },
    {
      "ÜNİTE": "Kendini İfade Etme",
      "AY": "MART",
      "HAFTA": "30. Hafta:\n30 Mart-03 Nisan",
      "SAAT": "3",
      "KONU": "5.   Olumlu İfadeler",
      "BELİRLİ GÜN VE HAFTALAR": "Kütüphaneler Haftası Kanser Haftası Dünya Otizm Farkındalık Günü",
      "KAZANIM": "İletişimde olumlu ifadeler kullanmanın önemini tartışır."
    },
    {
      "ÜNİTE": "Kendini İfade Etme",
      "AY": "NISAN",
      "HAFTA": "31. Hafta:\n06-10 Nisan",
      "SAAT": "3",
      "KONU": "1.   Konuşma ve İletişim",
      "BELİRLİ GÜN VE HAFTALAR": "Kanser Haftası Dünya Sağlık GününDünya Sağlık Haftası Kişisel Verileri Koruma Günü",
      "KAZANIM": "2. Dönem 1. Sınav  Konuşmanın iletişim sürecindeki önemini örneklerle açıklar."
    },
    {
      "ÜNİTE": "Güzel Konuşma",
      "AY": "NISAN",
      "HAFTA": "32. Hafta:\n13-17 Nisan",
      "SAAT": "3",
      "KONU": "1.   Nefes",
      "BELİRLİ GÜN VE HAFTALAR": "Turizm Haftası",
      "KAZANIM": "Nefes çalışmaları yapar.\nGevşeme hareketleri uygulanır.\n     Nefes egzersizleri yaptırılır.\n     Doğru nefes alma teknikleri uygulanır."
    },
    {
      "ÜNİTE": "Güzel Konuşma",
      "AY": "NISAN",
      "HAFTA": "33. Hafta:\n20-24 Nisan",
      "SAAT": "3",
      "KONU": "4.   Vurgu Tonlama Duraklama ve Ulama",
      "BELİRLİ GÜN VE HAFTALAR": "Ulusal Egemenlik ve Çocuk Bayramı",
      "KAZANIM": "Vurgu tonlama duraklama ve ulama çalışmaları yapar.\nVurgu ve tonlama kavramları açıklanır.\n     Vurgu türleri açıklanır."
    },
    {
      "ÜNİTE": "Güzel Konuşma",
      "AY": "NISAN",
      "HAFTA": "34. Hafta:\n27 Nisan-01 Mayıs",
      "SAAT": "3",
      "KONU": "2.   Ses ve Söyleyiş",
      "BELİRLİ GÜN VE HAFTALAR": "Kûtül Amâre Zaferi",
      "KAZANIM": "Ses ve söyleyiş çalışmaları yapar.\nSes kavramı ve sesin oluşumu açıklanır."
    },
    {
      "ÜNİTE": "Güzel Konuşma",
      "AY": "MAYIS",
      "HAFTA": "35. Hafta:\n04-08 Mayıs",
      "SAAT": "3",
      "KONU": "2.   Ses ve Söyleyiş",
      "BELİRLİ GÜN VE HAFTALAR": "Bilişim Haftası Trafik ve İlkyardım Haftası İş Sağlığı ve Güvenliği Haftası",
      "KAZANIM": "Ses ve söyleyiş çalışmaları yapar.\nSes ve harfin ayırımı açıklanır."
    },
    {
      "ÜNİTE": "Güzel Konuşma",
      "AY": "MAYIS",
      "HAFTA": "36. Hafta:\n11-15 Mayıs",
      "SAAT": "3",
      "KONU": "4.   Vurgu Tonlama Duraklama ve Ulama",
      "BELİRLİ GÜN VE HAFTALAR": "Engelliler Haftası Vakıflar Haftası",
      "KAZANIM": "Vurgu tonlama duraklama ve ulama çalışmaları yapar.\nKelime ve cümle vurguları ile ilgili alıştırmalar uygulatılır.\n     Vurgu ve tonlama çalışma örneklerinin incelenmesi sağlanır."
    },
    {
      "ÜNİTE": "Güzel Konuşma",
      "AY": "MAYIS",
      "HAFTA": "37. Hafta:\n18-22 Mayıs",
      "SAAT": "3",
      "KONU": "2.   Ses ve Söyleyiş",
      "BELİRLİ GÜN VE HAFTALAR": "Müzeler Haftası Atatürkü Anma ve Gençlik ve Spor Bayramı",
      "KAZANIM": "Ses ve söyleyiş çalışmaları yapar.\nTürkçedeki ünlü seslerin doğru kullanımı açıklanır."
    },
    {
      "ÜNİTE": "Güzel Konuşma",
      "AY": "MAYIS",
      "HAFTA": "38. Hafta:\n25-29 Mayıs",
      "SAAT": "3",
      "KONU": "3.   BoğumlamaArtikülasyon",
      "BELİRLİ GÜN VE HAFTALAR": "Etik Günü İstanbulun Fethi",
      "KAZANIM": "Boğumlama Artikülâsyon çalışmaları yapar.\nTelaffuz ve boğumlama kavramları açıklanır.\n   Telaffuz ve boğumlama kusurları açıklanır."
    },
    {
      "ÜNİTE": "Güzel Konuşma",
      "AY": "HAZIRAN",
      "HAFTA": "39. Hafta:\n01-05 Haziran",
      "SAAT": "3",
      "KONU": "4.   Vurgu Tonlama Duraklama ve Ulama",
      "BELİRLİ GÜN VE HAFTALAR": "Etik Günü Hayat Boyu Öğrenme Haftası",
      "KAZANIM": "2. Dönem 2. Sınav  Vurgu tonlama duraklama ve ulama çalışmaları yapar.\nTonlama alıştırmaları uygulatılır.\n     Konuşma hızını ayarlamanın önemi açıklanır."
    },
    {
      "ÜNİTE": "Güzel Konuşma",
      "AY": "HAZIRAN",
      "HAFTA": "40. Hafta:\n08-12 Haziran",
      "SAAT": "3",
      "KONU": "2.   Ses ve Söyleyiş",
      "BELİRLİ GÜN VE HAFTALAR": "Etik Günü Çevre ve İklim Değişikliği Haftası",
      "KAZANIM": "Ses ve söyleyiş çalışmaları yapar.\nTürkçedeki ünsüz seslerin doğru telaffuz şekilleri açıklanır."
    },
    {
      "ÜNİTE": "Güzel Konuşma",
      "AY": "HAZIRAN",
      "HAFTA": "41. Hafta:\n15-19 Haziran",
      "SAAT": "3",
      "KONU": "4.   Vurgu Tonlama Duraklama ve Ulama",
      "BELİRLİ GÜN VE HAFTALAR": "Etik Günü",
      "KAZANIM": "Vurgu tonlama duraklama ve ulama çalışmaları yapar.\nKonuşma hızını ayarlama ile ilgili alıştırmalar uygulatılır.\n     Durak ve duraklama kavramları açıklanır."
    },
    {
      "ÜNİTE": "Etkinlik Haftası",
      "AY": "HAZIRAN",
      "HAFTA": "42. Hafta:\n22-26 Haziran",
      "SAAT": "3",
      "KONU": "Etkinlik Haftası",
      "BELİRLİ GÜN VE HAFTALAR": "Etik Günü",
      "KAZANIM": "Etkinlik Haftası"
    },
    {
      "KONU": "* * Bu plan Talim Terbiye Kurulunun yayınladığı Çerçeve Öğretim Programı ve Ders Bilgi Formlarına göre hazırlanmıştır. ATATÜRKÇÜLÜK konuları ile ilgili olarak Talim ve Terbiye Kurulu Başkanlığının 2104 ve 2488 sayılı Tebliğler Dergisinden yararlanılmıştır."
    }
  ]
}